git_changelog-2.7.1.dist-info/METADATA
git_changelog-2.7.1.dist-info/WHEEL
git_changelog-2.7.1.dist-info/entry_points.txt
git_changelog-2.7.1.dist-info/licenses/LICENSE
git_changelog/__init__.py
git_changelog/__main__.py
git_changelog/_internal/__init__.py
git_changelog/_internal/build.py
git_changelog/_internal/cli.py
git_changelog/_internal/commit.py
git_changelog/_internal/debug.py
git_changelog/_internal/providers.py
git_changelog/_internal/templates/__init__.py
git_changelog/_internal/templates/angular.md.jinja
git_changelog/_internal/templates/keepachangelog.md.jinja
git_changelog/_internal/versioning.py
git_changelog/build.py
git_changelog/cli.py
git_changelog/commit.py
git_changelog/providers.py
git_changelog/py.typed
git_changelog/templates.py
git_changelog/versioning.py
git_changelog-2.7.1.dist-info/RECORD
