Metadata-Version: 2.4
Name: git-changelog
Version: 2.7.1
Summary: Automatic Changelog generator using Jinja2 templates.
Keywords: git,changelog,changelog-generator,commit-style,commit-convention
Author-Email: =?utf-8?q?Timoth=C3=A9e_Mazzucotelli?= <dev@pawamoy.fr>
License-Expression: ISC
License-File: LICENSE
Classifier: Development Status :: 4 - Beta
Classifier: Intended Audience :: Developers
Classifier: Programming Language :: Python
Classifier: Programming Language :: Python :: 3
Classifier: Programming Language :: Python :: 3 :: Only
Classifier: Programming Language :: Python :: 3.10
Classifier: Programming Language :: Python :: 3.11
Classifier: Programming Language :: Python :: 3.12
Classifier: Programming Language :: Python :: 3.13
Classifier: Programming Language :: Python :: 3.14
Classifier: Topic :: Documentation
Classifier: Topic :: Software Development
Classifier: Topic :: Software Development :: Documentation
Classifier: Topic :: Utilities
Classifier: Typing :: Typed
Project-URL: Homepage, https://pawamoy.github.io/git-changelog
Project-URL: Documentation, https://pawamoy.github.io/git-changelog
Project-URL: Changelog, https://pawamoy.github.io/git-changelog/changelog
Project-URL: Repository, https://github.com/pawamoy/git-changelog
Project-URL: Issues, https://github.com/pawamoy/git-changelog/issues
Project-URL: Discussions, https://github.com/pawamoy/git-changelog/discussions
Project-URL: Gitter, https://gitter.im/git-changelog/community
Project-URL: Funding, https://github.com/sponsors/pawamoy
Requires-Python: >=3.10
Requires-Dist: Jinja2>=3.0
Requires-Dist: packaging>=26.0
Requires-Dist: platformdirs>=4.4
Requires-Dist: semver>=3.0
Requires-Dist: tomli>=2.0; python_version < "3.11"
Requires-Dist: typing-extensions>=4.9; python_version < "3.13"
